Workbook
Name Slicer_Brand: #N/A
Name Slicer_Category: #N/A
Name Slicer_Month: #N/A
Name Slicer_Payment_Mode: #N/A
Name Slicer_Sales_Channel: #N/A
Name Slicer_State: #N/A

Sheet SalesData
A1: Order ID | B1: Order Date | C1: Month | D1: Customer Name | E1: Customer ID | F1: Gender | G1: Age | H1: State | I1: City | J1: Category | K1: Sub Category | L1: Product | M1: Brand | N1: Size | O1: Color | P1: Quantity | Q1: Unit Cost | R1: Unit Price | S1: Discount % | T1: Sales | U1: Cost | V1: Profit | W1: Payment Mode | X1: Sales Channel | Y1: Order Status
A2: ORD1001 | B2: 23-10-2025 | C2: =TEXT(B2, "MMMM") -> October | D2: Pooja | E2: CUST174 | F2: Female | G2: 54 | H2: Rajasthan | I2: Jaipur | J2: Kids | K2: Tshirt | L2: Tshirt | M2: Roadster | N2: XL | O2: White | P2: 4 | Q2: 1092 | R2: 1672 | S2: 5 | T2: =P2*R2*(1-S2/100) -> 6353.6 | U2: =P2*Q2 -> 4368 | V2: =T2-U2 -> 1985.6 | W2: Cash | X2: Offline | Y2: Delivered
A3: ORD1002 | B3: 26-08-2025 | C3: =TEXT(B3, "MMMM") -> August | D3: Vikas | E3: CUST165 | F3: Female | G3: 26 | H3: Maharashtra | I3: Mumbai | J3: Kids | K3: Tshirt | L3: Tshirt | M3: Roadster | N3: M | O3: Blue | P3: 1 | Q3: 699 | R3: 879 | S3: 0 | T3: =P3*R3*(1-S3/100) -> 879 | U3: =P3*Q3 -> 699 | V3: =T3-U3 -> 180 | W3: UPI | X3: Online | Y3: Returned
A4: ORD1003 | B4: 19-11-2025 | C4: =TEXT(B4, "MMMM") -> November | D4: Amit | E4: CUST148 | F4: Male | G4: 22 | H4: Delhi | I4: Delhi | J4: Women | K4: Kurti | L4: Kurti | M4: Biba | N4: S | O4: Black | P4: 3 | Q4: 1244 | R4: 1730 | S4: 15 | T4: =P4*R4*(1-S4/100) -> 4411.5 | U4: =P4*Q4 -> 3732 | V4: =T4-U4 -> 679.5 | W4: Cash | X4: Offline | Y4: Delivered
A5: ORD1004 | B5: 10-05-2025 | C5: =TEXT(B5, "MMMM") -> May | D5: Neha | E5: CUST146 | F5: Male | G5: 42 | H5: Karnataka | I5: Bengaluru | J5: Women | K5: Saree | L5: Saree | M5: Puma | N5: S | O5: Blue | P5: 3 | Q5: 439 | R5: 862 | S5: 15 | T5: =P5*R5*(1-S5/100) -> 2198.1 | U5: =P5*Q5 -> 1317 | V5: =T5-U5 -> 881.1 | W5: Card | X5: Offline | Y5: Delivered
A6: ORD1005 | B6: 23-10-2025 | C6: =TEXT(B6, "MMMM") -> October | D6: Sumit | E6: CUST179 | F6: Female | G6: 39 | H6: Delhi | I6: Delhi | J6: Kids | K6: Tshirt | L6: Tshirt | M6: Biba | N6: L | O6: Green | P6: 2 | Q6: 1290 | R6: 2012 | S6: 5 | T6: =P6*R6*(1-S6/100) -> 3822.8 | U6: =P6*Q6 -> 2580 | V6: =T6-U6 -> 1242.8 | W6: Cash | X6: Offline | Y6: Delivered
A7: ORD1006 | B7: 27-01-2025 | C7: =TEXT(B7, "MMMM") -> January | D7: Pooja | E7: CUST178 | F7: Female | G7: 49 | H7: Karnataka | I7: Bengaluru | J7: Women | K7: Saree | L7: Saree | M7: Biba | N7: XL | O7: Green | P7: 4 | Q7: 417 | R7: 653 | S7: 10 | T7: =P7*R7*(1-S7/100) -> 2350.8 | U7: =P7*Q7 -> 1668 | V7: =T7-U7 -> 682.8 | W7: UPI | X7: Online | Y7: Returned
A8: ORD1007 | B8: 30-05-2025 | C8: =TEXT(B8, "MMMM") -> May | D8: Sneha | E8: CUST115 | F8: Male | G8: 39 | H8: Delhi | I8: Delhi | J8: Men | K8: Shirts | L8: Shirts | M8: Nike | N8: S | O8: Blue | P8: 2 | Q8: 640 | R8: 1133 | S8: 15 | T8: =P8*R8*(1-S8/100) -> 1926.1 | U8: =P8*Q8 -> 1280 | V8: =T8-U8 -> 646.1 | W8: UPI | X8: Offline | Y8: Delivered
A9: ORD1008 | B9: 29-05-2025 | C9: =TEXT(B9, "MMMM") -> May | D9: Priya | E9: CUST115 | F9: Female | G9: 24 | H9: Rajasthan | I9: Jaipur | J9: Men | K9: Shirts | L9: Shirts | M9: Levis | N9: S | O9: White | P9: 3 | Q9: 1483 | R9: 1766 | S9: 0 | T9: =P9*R9*(1-S9/100) -> 5298 | U9: =P9*Q9 -> 4449 | V9: =T9-U9 -> 849 | W9: UPI | X9: Offline | Y9: Delivered
A10: ORD1009 | B10: 02-12-2025 | C10: =TEXT(B10, "MMMM") -> December | D10: Rohit | E10: CUST134 | F10: Male | G10: 45 | H10: Uttar Pradesh | I10: Lucknow | J10: Kids | K10: Tshirt | L10: Tshirt | M10: Levis | N10: XL | O10: Green | P10: 2 | Q10: 814 | R10: 1422 | S10: 10 | T10: =P10*R10*(1-S10/100) -> 2559.6 | U10: =P10*Q10 -> 1628 | V10: =T10-U10 -> 931.6 | W10: Card | X10: Online | Y10: Delivered
A11: ORD1010 | B11: 05-03-2025 | C11: =TEXT(B11, "MMMM") -> March | D11: Pooja | E11: CUST188 | F11: Female | G11: 36 | H11: Delhi | I11: Delhi | J11: Kids | K11: Tshirt | L11: Tshirt | M11: Puma | N11: XL | O11: Green | P11: 1 | Q11: 1358 | R11: 2118 | S11: 10 | T11: =P11*R11*(1-S11/100) -> 1906.2 | U11: =P11*Q11 -> 1358 | V11: =T11-U11 -> 548.2 | W11: UPI | X11: Offline | Y11: Returned
A12: ORD1011 | B12: 28-11-2025 | C12: =TEXT(B12, "MMMM") -> November | D12: Anjali | E12: CUST157 | F12: Female | G12: 26 | H12: Rajasthan | I12: Jaipur | J12: Kids | K12: Shorts | L12: Shorts | M12: Biba | N12: S | O12: White | P12: 4 | Q12: 357 | R12: 533 | S12: 15 | T12: =P12*R12*(1-S12/100) -> 1812.2 | U12: =P12*Q12 -> 1428 | V12: =T12-U12 -> 384.2 | W12: UPI | X12: Offline | Y12: Returned
A13: ORD1012 | B13: 31-10-2025 | C13: =TEXT(B13, "MMMM") -> October | D13: Priya | E13: CUST173 | F13: Male | G13: 23 | H13: Uttar Pradesh | I13: Lucknow | J13: Kids | K13: Shorts | L13: Shorts | M13: Nike | N13: XL | O13: Green | P13: 5 | Q13: 1292 | R13: 1961 | S13: 5 | T13: =P13*R13*(1-S13/100) -> 9314.75 | U13: =P13*Q13 -> 6460 | V13: =T13-U13 -> 2854.75 | W13: Card | X13: Offline | Y13: Delivered
... A201: ORD1200 | B201: 22-05-2025 | C201: =TEXT(B201, "MMMM") -> May | D201: Pooja | E201: CUST160 | F201: Male | G201: 21 | H201: Maharashtra | I201: Mumbai | J201: Kids | K201: Shorts | L201: Shorts | M201: Biba | N201: M | O201: Green | P201: 1 | Q201: 443 | R201: 864 | S201: 20 | T201: =P201*R201*(1-S201/100) -> 691.2 | U201: =P201*Q201 -> 443 | V201: =T201-U201 -> 248.2 | W201: UPI | X201: Offline | Y201: Returned

Sheet PT_Brand
A3: Brand | B3: Sum of Sales
A4: Biba | B4: 164298.5
A5: Levis | B5: 126774
A6: Nike | B6: 145086.85
A7: Puma | B7: 160168.7
A8: Roadster | B8: 111277.85

Sheet PT_Category
A3: Category | B3: Sum of Sales
A4: Kids | B4: 296225.55
A5: Men | B5: 195510.6
A6: Women | B6: 215869.75

Sheet Dashboard
A1: A | B1: B | E1: Clothing Sales Dashboard
A2: Total Sales | B2: =SUM(SalesData!T2:T201) -> 707605.9
A3: Total Cost | B3: =SUM(SalesData!U2:U201) -> 523381
A4: Total Profit | B4: =SUM(SalesData!V2:V201) -> 184224.9
A5: Total Orders | B5: =COUNTA(SalesData!A2:A201) -> 200
A6: Average Sales | B6: =AVERAGE(SalesData!T2:T201) -> 3538.0295
A7: Profit Margin % | B7: =SUM(SalesData!V2:V201)/SUM(SalesData!T2:T201) -> 0.26034958
A8: Average Discount % | B8: =AVERAGE(SalesData!S2:S201) -> 10.6
D9: Total Sales | H9: Total Cost | L9: Total Profit | P9: Total Orders
D11: =GETPIVOTDATA("Sales",KPI!$A$3) -> 707605.9 | H11: =GETPIVOTDATA("Sum of Cost",KPI!$A$3) -> 523381 | L11: =GETPIVOTDATA("Sum of Profit",KPI!$A$3) -> 184224.9 | P11: =GETPIVOTDATA("Count of Order ID",KPI!$A$3) -> 200
F15: Average Sales | J15: Profit Margin % | N15: Average Discount%
F17: =GETPIVOTDATA("Average of Sales2",KPI!$A$3) -> 3538.0295 | J17: =B7 -> 0.26034958 | N17: =GETPIVOTDATA("Average of Discount %",KPI!$A$3) -> 10.6

Sheet PT_State
A3: Row Labels | B3: Sum of Sales
A4: Delhi | B4: 149394.45
A5: Karnataka | B5: 138937.65
A6: Maharashtra | B6: 122270.9
A7: Rajasthan | B7: 156242.6
A8: Uttar Pradesh | B8: 140760.3

Sheet PT_Payment Mode
A3: Row Labels | B3: Sum of Sales
A4: Card | B4: 188555.35
A5: Cash | B5: 230875.75
A6: UPI | B6: 288174.8

Sheet PT_Channel
A3: Row Labels | B3: Sum of Sales
A4: Offline | B4: 371859.05
A5: Online | B5: 335746.85

Sheet PT_Monthly
A3: Row Labels | B3: Sum of Sales
A4: January | B4: 78034.85
A5: February | B5: 47629.65
A6: March | B6: 89172.9
A7: April | B7: 36000.8
A8: May | B8: 63525.1
A9: June | B9: 36488.3
A10: July | B10: 71423.8
A11: August | B11: 74943.4
A12: September | B12: 22611.3
A13: October | B13: 92009.25
A14: November | B14: 39292.05
A15: December | B15: 56474.5

Sheet KPI
A3: Sum of Sales | B3: Sum of Cost | C3: Count of Order ID | D3: Sum of Profit | E3: Average of Discount % | F3: Average of Sales2
A4: 707605.9 | B4: 523381 | C4: 200 | D4: 184224.9 | E4: 10.6 | F4: 3538.0295
